setup.py
ds_common.egg-info/PKG-INFO
ds_common.egg-info/SOURCES.txt
ds_common.egg-info/dependency_links.txt
ds_common.egg-info/not-zip-safe
ds_common.egg-info/top_level.txt
ds_http/__init__.py
ds_http/ds_http.py
ds_http/ds_https.py