Metadata-Version: 1.0
Name: ds-common
Version: 0.0.3
Summary: Common services for DataSHIELD Poll-Qua mechanism
Home-page: https://github.com/juliangruendner/ds_common
Author: Julian Gruendner
Author-email: julian.gruendner@fau.de 
License: GNU
Platform: UNKNOWN
